Metadata-Version: 2.1
Name: pykural
Version: 1.0.2
Summary: Thirukkural for Python. பைதானில் திருக்குறள் !
Home-page: https://github.com/coderganesh/pykural
Author: Ganesh Kumar T K
Author-email: ganeshkumartk@outlook.com
License: MIT
Keywords: Tamil,Thirukkural,pykural,திருக்குறள்
Platform: UNKNOWN
Classifier: Operating System :: OS Independent
Classifier: Programming Language :: Python :: 3
Classifier: Programming Language :: Python :: 3.4
Classifier: Programming Language :: Python :: 3.5
Classifier: Programming Language :: Python :: 3.6
Classifier: Programming Language :: Python :: 3.7
